robodog/__init__.py
robodog/base.py
robodog/cli.py
robodog/diff_service.py
robodog/file_service.py
robodog/file_watcher.py
robodog/mcphandler.py
robodog/models.py
robodog/parse_service.py
robodog/prompt_builder.py
robodog/service.py
robodog/task_manager.py
robodog/task_parser.py
robodog/todo.py
robodogcli-2.6.16.dist-info/METADATA
robodogcli-2.6.16.dist-info/WHEEL
robodogcli-2.6.16.dist-info/top_level.txt
robodogcli-2.6.16.dist-info/RECORD
